setup.py
sugar_badges.py
sugar_badges.egg-info/PKG-INFO
sugar_badges.egg-info/SOURCES.txt
sugar_badges.egg-info/dependency_links.txt
sugar_badges.egg-info/top_level.txt