Metadata-Version: 1.0
Name: sugar-badges
Version: 0.1.1
Summary: Award badges in Sugar
Home-page: http://github.com/FOSSRIT/sugar-badges
Author: David Wilson
Author-email: daw4475@rit.edu
License: MIT
Platform: UNKNOWN
